superpehasher/__init__.py
superpehasher/superpehasher.py
superpehasher-0.6.dist-info/METADATA
superpehasher-0.6.dist-info/WHEEL
superpehasher-0.6.dist-info/top_level.txt
superpehasher-0.6.dist-info/RECORD
