Metadata-Version: 2.1
Name: superpehasher
Version: 0.6
Summary: SuperPEHasher is a wrapper written in Python3 for several hash algorithms dedicated to PE file.
Home-page: https://github.com/fr0gger/SuperPeHasher
Author: Thomas Roccia @fr0gger_
License: Apache
Keywords: hashes,md5,sha256
Platform: UNKNOWN
Classifier: Development Status :: 5 - Production/Stable
Classifier: Intended Audience :: Developers
Classifier: License :: OSI Approved :: Apache Software License
Classifier: Programming Language :: Python :: 3
Requires-Dist: mmh3
Requires-Dist: pefile
Requires-Dist: pyimpfuzzy
Requires-Dist: ssdeep
Requires-Dist: r2pipe
Requires-Dist: bitstring
